{
	"categories":[
		{
			"id": 0,
			"name": "Tech",
			"color": "blue"
		},
		{
			"id": 1,
			"name": "Finance",
			"color": "red"
		}
	], 
	"talks": [
		{
			"categoryId": 0,
			"title": "Arbeta med prototyper",
			"speaker": "Samuel",
			"time": "10.00-10.10",
			"date": "SEP 20",
			"location": "Room 11",
			"country": "Sweden"
		},
		{
			"categoryId": 1,
			"title": "The Zen of time reporting",
			"speaker": "Magnus Sundberg",
			"time": "10.00-10.10",
			"date": "SEP 20",
			"location": "Room 11",
			"country": "Sweden"
		}
	]
}